{
    "graph": [
        {
            "author": " Phil Carlisle",
            "cards": [
                {
                    "active": true,
                    "cardid": "17891131-5ab5-11e9-a39d-000d3ab1e588",
                    "component_id": "f05e4d3a-53c1-11e8-b0ea-784f435179ea",
                    "config": null,
                    "constraints": [],
                    "cssclass": null,
                    "description": "",
                    "graph_id": "1789112e-5ab5-11e9-8519-000d3ab1e588",
                    "helpenabled": false,
                    "helptext": null,
                    "helptitle": null,
                    "instructions": "Used to record the details of the last known Voyage of an aircraft.",
                    "is_editable": true,
                    "name": "Warden_Crash_Event",
                    "nodegroup_id": "1789112f-5ab5-11e9-b464-000d3ab1e588",
                    "sortorder": null,
                    "visible": true
                },
                {
                    "active": true,
                    "cardid": "17891134-5ab5-11e9-b0a6-000d3ab1e588",
                    "component_id": "f05e4d3a-53c1-11e8-b0ea-784f435179ea",
                    "config": null,
                    "constraints": [],
                    "cssclass": null,
                    "description": "",
                    "graph_id": "1789112e-5ab5-11e9-8519-000d3ab1e588",
                    "helpenabled": false,
                    "helptext": null,
                    "helptitle": null,
                    "instructions": null,
                    "is_editable": true,
                    "name": "Voyage Details",
                    "nodegroup_id": "17891132-5ab5-11e9-9168-000d3ab1e588",
                    "sortorder": null,
                    "visible": true
                },
                {
                    "active": true,
                    "cardid": "17891137-5ab5-11e9-b27e-000d3ab1e588",
                    "component_id": "f05e4d3a-53c1-11e8-b0ea-784f435179ea",
                    "config": null,
                    "constraints": [],
                    "cssclass": null,
                    "description": "Represents a single node in a graph",
                    "graph_id": "1789112e-5ab5-11e9-8519-000d3ab1e588",
                    "helpenabled": false,
                    "helptext": null,
                    "helptitle": null,
                    "instructions": null,
                    "is_editable": true,
                    "name": "Cargo",
                    "nodegroup_id": "17891135-5ab5-11e9-921e-000d3ab1e588",
                    "sortorder": null,
                    "visible": true
                }
            ],
            "cards_x_nodes_x_widgets": [
                {
                    "card_id": "17891131-5ab5-11e9-a39d-000d3ab1e588",
                    "config": {
                        "defaultValue": "",
                        "label": "Manner of Loss",
                        "options": [],
                        "placeholder": "Select an option"
                    },
                    "id": "1789114b-5ab5-11e9-a23d-000d3ab1e588",
                    "label": "Manner of Loss",
                    "node_id": "17891149-5ab5-11e9-b0c3-000d3ab1e588",
                    "sortorder": 5,
                    "visible": true,
                    "widget_id": "10000000-0000-0000-0000-000000000002"
                },
                {
                    "card_id": "17891137-5ab5-11e9-b27e-000d3ab1e588",
                    "config": {
                        "defaultValue": "",
                        "label": "Cargo Type",
                        "options": [],
                        "placeholder": "Select an option"
                    },
                    "id": "1789114c-5ab5-11e9-86f8-000d3ab1e588",
                    "label": "Cargo Type",
                    "node_id": "1789113e-5ab5-11e9-a068-000d3ab1e588",
                    "sortorder": 0,
                    "visible": true,
                    "widget_id": "10000000-0000-0000-0000-000000000012"
                },
                {
                    "card_id": "17891131-5ab5-11e9-a39d-000d3ab1e588",
                    "config": {
                        "defaultValue": "",
                        "label": "Place of Departure Name",
                        "options": [],
                        "placeholder": "Select an option"
                    },
                    "id": "1789114d-5ab5-11e9-9c55-000d3ab1e588",
                    "label": "Place of Departure Name",
                    "node_id": "17891148-5ab5-11e9-b825-000d3ab1e588",
                    "sortorder": 6,
                    "visible": true,
                    "widget_id": "10000000-0000-0000-0000-000000000002"
                },
                {
                    "card_id": "17891131-5ab5-11e9-a39d-000d3ab1e588",
                    "config": {
                        "defaultValue": "",
                        "label": "Place of Destination Name",
                        "options": [],
                        "placeholder": "Select an option"
                    },
                    "id": "1789114e-5ab5-11e9-bfc4-000d3ab1e588",
                    "label": "Place of Destination Name",
                    "node_id": "17891147-5ab5-11e9-aa2f-000d3ab1e588",
                    "sortorder": 7,
                    "visible": true,
                    "widget_id": "10000000-0000-0000-0000-000000000002"
                },
                {
                    "card_id": "17891131-5ab5-11e9-a39d-000d3ab1e588",
                    "config": {
                        "dateFormat": "YYYY-MM-DD",
                        "defaultValue": "",
                        "label": "Expected Date of Arrival",
                        "maxDate": false,
                        "minDate": false,
                        "placeholder": "Enter date",
                        "viewMode": "days"
                    },
                    "id": "1789114f-5ab5-11e9-8df3-000d3ab1e588",
                    "label": "Expected Date of Arrival",
                    "node_id": "17891141-5ab5-11e9-a4a7-000d3ab1e588",
                    "sortorder": 3,
                    "visible": true,
                    "widget_id": "10000000-0000-0000-0000-000000000004"
                },
                {
                    "card_id": "17891131-5ab5-11e9-a39d-000d3ab1e588",
                    "config": {
                        "defaultValue": "",
                        "label": "Site Type",
                        "options": [],
                        "placeholder": "Select an option"
                    },
                    "id": "17891150-5ab5-11e9-a700-000d3ab1e588",
                    "label": "Site Type",
                    "node_id": "17891143-5ab5-11e9-9139-000d3ab1e588",
                    "sortorder": 0,
                    "visible": true,
                    "widget_id": "10000000-0000-0000-0000-000000000002"
                },
                {
                    "card_id": "17891131-5ab5-11e9-a39d-000d3ab1e588",
                    "config": {
                        "dateFormat": "YYYY-MM-DD",
                        "defaultValue": "",
                        "label": "Date of Loss",
                        "maxDate": false,
                        "minDate": false,
                        "placeholder": "Enter date",
                        "viewMode": "days"
                    },
                    "id": "17891151-5ab5-11e9-b781-000d3ab1e588",
                    "label": "Date of Loss",
                    "node_id": "1789113f-5ab5-11e9-9c10-000d3ab1e588",
                    "sortorder": 4,
                    "visible": true,
                    "widget_id": "10000000-0000-0000-0000-000000000004"
                },
                {
                    "card_id": "17891131-5ab5-11e9-a39d-000d3ab1e588",
                    "config": {
                        "defaultValue": "",
                        "label": "Voyage Type",
                        "options": [],
                        "placeholder": "Select an option"
                    },
                    "id": "17891152-5ab5-11e9-b7d0-000d3ab1e588",
                    "label": "Voyage Type",
                    "node_id": "1789114a-5ab5-11e9-8b04-000d3ab1e588",
                    "sortorder": 1,
                    "visible": true,
                    "widget_id": "10000000-0000-0000-0000-000000000002"
                },
                {
                    "card_id": "17891134-5ab5-11e9-b0a6-000d3ab1e588",
                    "config": {
                        "defaultValue": "",
                        "label": "Description",
                        "maxLength": null,
                        "placeholder": "Enter text",
                        "width": "100%"
                    },
                    "id": "17891153-5ab5-11e9-9d1e-000d3ab1e588",
                    "label": "Description",
                    "node_id": "17891138-5ab5-11e9-a583-000d3ab1e588",
                    "sortorder": 0,
                    "visible": true,
                    "widget_id": "10000000-0000-0000-0000-000000000001"
                },
                {
                    "card_id": "17891134-5ab5-11e9-b0a6-000d3ab1e588",
                    "config": {
                        "defaultValue": "",
                        "label": "Description Type",
                        "options": [],
                        "placeholder": "Select an option"
                    },
                    "id": "17891154-5ab5-11e9-bb78-000d3ab1e588",
                    "label": "Description Type",
                    "node_id": "17891139-5ab5-11e9-9b34-000d3ab1e588",
                    "sortorder": 1,
                    "visible": true,
                    "widget_id": "10000000-0000-0000-0000-000000000002"
                },
                {
                    "card_id": "17891131-5ab5-11e9-a39d-000d3ab1e588",
                    "config": {
                        "dateFormat": "YYYY-MM-DD",
                        "defaultValue": "",
                        "label": "Date of Departure",
                        "maxDate": false,
                        "minDate": false,
                        "placeholder": "Enter date",
                        "viewMode": "days"
                    },
                    "id": "17891155-5ab5-11e9-a5ae-000d3ab1e588",
                    "label": "Date of Departure",
                    "node_id": "17891145-5ab5-11e9-8d94-000d3ab1e588",
                    "sortorder": 2,
                    "visible": true,
                    "widget_id": "10000000-0000-0000-0000-000000000004"
                }
            ],
            "color": null,
            "config": {},
            "deploymentdate": null,
            "deploymentfile": null,
            "description": "",
            "edges": [
                {
                    "description": null,
                    "domainnode_id": "1789112f-5ab5-11e9-b464-000d3ab1e588",
                    "edgeid": "17891161-5ab5-11e9-9993-000d3ab1e588",
                    "graph_id": "1789112e-5ab5-11e9-8519-000d3ab1e588",
                    "name": null,
                    "ontologyproperty": "http://www.cidoc-crm.org/cidoc-crm/P92_brought_into_existence",
                    "rangenode_id": "17891144-5ab5-11e9-92e9-000d3ab1e588"
                },
                {
                    "description": null,
                    "domainnode_id": "1789112f-5ab5-11e9-b464-000d3ab1e588",
                    "edgeid": "17891162-5ab5-11e9-825a-000d3ab1e588",
                    "graph_id": "1789112e-5ab5-11e9-8519-000d3ab1e588",
                    "name": null,
                    "ontologyproperty": "http://www.cidoc-crm.org/cidoc-crm/P2_has_type",
                    "rangenode_id": "1789114a-5ab5-11e9-8b04-000d3ab1e588"
                },
                {
                    "description": null,
                    "domainnode_id": "17891132-5ab5-11e9-9168-000d3ab1e588",
                    "edgeid": "17891163-5ab5-11e9-8c6c-000d3ab1e588",
                    "graph_id": "1789112e-5ab5-11e9-8519-000d3ab1e588",
                    "name": null,
                    "ontologyproperty": "http://www.cidoc-crm.org/cidoc-crm/P3_has_note",
                    "rangenode_id": "17891138-5ab5-11e9-a583-000d3ab1e588"
                },
                {
                    "description": null,
                    "domainnode_id": "17891132-5ab5-11e9-9168-000d3ab1e588",
                    "edgeid": "17891164-5ab5-11e9-b46b-000d3ab1e588",
                    "graph_id": "1789112e-5ab5-11e9-8519-000d3ab1e588",
                    "name": null,
                    "ontologyproperty": "http://www.cidoc-crm.org/cidoc-crm/P2_has_type",
                    "rangenode_id": "17891139-5ab5-11e9-9b34-000d3ab1e588"
                },
                {
                    "description": null,
                    "domainnode_id": "17891144-5ab5-11e9-92e9-000d3ab1e588",
                    "edgeid": "17891165-5ab5-11e9-9d18-000d3ab1e588",
                    "graph_id": "1789112e-5ab5-11e9-8519-000d3ab1e588",
                    "name": null,
                    "ontologyproperty": "http://www.cidoc-crm.org/cidoc-crm/P2_has_type",
                    "rangenode_id": "17891143-5ab5-11e9-9139-000d3ab1e588"
                },
                {
                    "description": null,
                    "domainnode_id": "1789112f-5ab5-11e9-b464-000d3ab1e588",
                    "edgeid": "17891166-5ab5-11e9-9cfa-000d3ab1e588",
                    "graph_id": "1789112e-5ab5-11e9-8519-000d3ab1e588",
                    "name": null,
                    "ontologyproperty": "http://www.cidoc-crm.org/cidoc-crm/P141i_was_assigned_by",
                    "rangenode_id": "17891132-5ab5-11e9-9168-000d3ab1e588"
                },
                {
                    "description": null,
                    "domainnode_id": "17891142-5ab5-11e9-a89e-000d3ab1e588",
                    "edgeid": "17891167-5ab5-11e9-8991-000d3ab1e588",
                    "graph_id": "1789112e-5ab5-11e9-8519-000d3ab1e588",
                    "name": null,
                    "ontologyproperty": "http://www.cidoc-crm.org/cidoc-crm/P1_is_identified_by",
                    "rangenode_id": "1789113f-5ab5-11e9-9c10-000d3ab1e588"
                },
                {
                    "description": null,
                    "domainnode_id": "17891142-5ab5-11e9-a89e-000d3ab1e588",
                    "edgeid": "17891168-5ab5-11e9-9945-000d3ab1e588",
                    "graph_id": "1789112e-5ab5-11e9-8519-000d3ab1e588",
                    "name": null,
                    "ontologyproperty": "http://www.cidoc-crm.org/cidoc-crm/P1_is_identified_by",
                    "rangenode_id": "17891141-5ab5-11e9-a4a7-000d3ab1e588"
                },
                {
                    "description": null,
                    "domainnode_id": "1789112f-5ab5-11e9-b464-000d3ab1e588",
                    "edgeid": "17891169-5ab5-11e9-8f5b-000d3ab1e588",
                    "graph_id": "1789112e-5ab5-11e9-8519-000d3ab1e588",
                    "name": null,
                    "ontologyproperty": "http://www.cidoc-crm.org/cidoc-crm/P4_has_time-span",
                    "rangenode_id": "17891142-5ab5-11e9-a89e-000d3ab1e588"
                },
                {
                    "description": null,
                    "domainnode_id": "17891142-5ab5-11e9-a89e-000d3ab1e588",
                    "edgeid": "1789116a-5ab5-11e9-95d9-000d3ab1e588",
                    "graph_id": "1789112e-5ab5-11e9-8519-000d3ab1e588",
                    "name": null,
                    "ontologyproperty": "http://www.cidoc-crm.org/cidoc-crm/P1_is_identified_by",
                    "rangenode_id": "17891145-5ab5-11e9-8d94-000d3ab1e588"
                },
                {
                    "description": null,
                    "domainnode_id": "17891135-5ab5-11e9-921e-000d3ab1e588",
                    "edgeid": "17891156-5ab5-11e9-af7c-000d3ab1e588",
                    "graph_id": "1789112e-5ab5-11e9-8519-000d3ab1e588",
                    "name": null,
                    "ontologyproperty": "http://www.cidoc-crm.org/cidoc-crm/P2_has_type",
                    "rangenode_id": "1789113e-5ab5-11e9-a068-000d3ab1e588"
                },
                {
                    "description": null,
                    "domainnode_id": "1789112f-5ab5-11e9-b464-000d3ab1e588",
                    "edgeid": "17891157-5ab5-11e9-80c8-000d3ab1e588",
                    "graph_id": "1789112e-5ab5-11e9-8519-000d3ab1e588",
                    "name": null,
                    "ontologyproperty": "http://www.cidoc-crm.org/cidoc-crm/P12_occurred_in_the_presence_of",
                    "rangenode_id": "17891135-5ab5-11e9-921e-000d3ab1e588"
                },
                {
                    "description": null,
                    "domainnode_id": "1789112f-5ab5-11e9-b464-000d3ab1e588",
                    "edgeid": "17891158-5ab5-11e9-833f-000d3ab1e588",
                    "graph_id": "1789112e-5ab5-11e9-8519-000d3ab1e588",
                    "name": null,
                    "ontologyproperty": "http://www.cidoc-crm.org/cidoc-crm/P161_has_spatial_projection",
                    "rangenode_id": "17891140-5ab5-11e9-84ed-000d3ab1e588"
                },
                {
                    "description": null,
                    "domainnode_id": "1789112f-5ab5-11e9-b464-000d3ab1e588",
                    "edgeid": "17891159-5ab5-11e9-8014-000d3ab1e588",
                    "graph_id": "1789112e-5ab5-11e9-8519-000d3ab1e588",
                    "name": null,
                    "ontologyproperty": "http://www.cidoc-crm.org/cidoc-crm/P161_has_spatial_projection",
                    "rangenode_id": "17891146-5ab5-11e9-a3a2-000d3ab1e588"
                },
                {
                    "description": null,
                    "domainnode_id": "1789113a-5ab5-11e9-a3b4-000d3ab1e588",
                    "edgeid": "1789115a-5ab5-11e9-82ec-000d3ab1e588",
                    "graph_id": "1789112e-5ab5-11e9-8519-000d3ab1e588",
                    "name": null,
                    "ontologyproperty": "http://www.cidoc-crm.org/cidoc-crm/P107_has_current_or_former_member",
                    "rangenode_id": "1789113b-5ab5-11e9-ac12-000d3ab1e588"
                },
                {
                    "description": null,
                    "domainnode_id": "1789113b-5ab5-11e9-ac12-000d3ab1e588",
                    "edgeid": "1789115b-5ab5-11e9-a315-000d3ab1e588",
                    "graph_id": "1789112e-5ab5-11e9-8519-000d3ab1e588",
                    "name": null,
                    "ontologyproperty": "http://www.cidoc-crm.org/cidoc-crm/P2_has_type",
                    "rangenode_id": "1789113c-5ab5-11e9-b9c3-000d3ab1e588"
                },
                {
                    "description": null,
                    "domainnode_id": "1789113b-5ab5-11e9-ac12-000d3ab1e588",
                    "edgeid": "1789115c-5ab5-11e9-a1dd-000d3ab1e588",
                    "graph_id": "1789112e-5ab5-11e9-8519-000d3ab1e588",
                    "name": null,
                    "ontologyproperty": "http://www.cidoc-crm.org/cidoc-crm/P1_is_identified_by",
                    "rangenode_id": "1789113d-5ab5-11e9-8c49-000d3ab1e588"
                },
                {
                    "description": null,
                    "domainnode_id": "1789112f-5ab5-11e9-b464-000d3ab1e588",
                    "edgeid": "1789115d-5ab5-11e9-8c64-000d3ab1e588",
                    "graph_id": "1789112e-5ab5-11e9-8519-000d3ab1e588",
                    "name": null,
                    "ontologyproperty": "http://www.cidoc-crm.org/cidoc-crm/P11_had_participant",
                    "rangenode_id": "1789113a-5ab5-11e9-a3b4-000d3ab1e588"
                },
                {
                    "description": null,
                    "domainnode_id": "1789112f-5ab5-11e9-b464-000d3ab1e588",
                    "edgeid": "1789115e-5ab5-11e9-952d-000d3ab1e588",
                    "graph_id": "1789112e-5ab5-11e9-8519-000d3ab1e588",
                    "name": null,
                    "ontologyproperty": "http://www.cidoc-crm.org/cidoc-crm/P2_has_type",
                    "rangenode_id": "17891149-5ab5-11e9-b0c3-000d3ab1e588"
                },
                {
                    "description": null,
                    "domainnode_id": "17891146-5ab5-11e9-a3a2-000d3ab1e588",
                    "edgeid": "1789115f-5ab5-11e9-b2a7-000d3ab1e588",
                    "graph_id": "1789112e-5ab5-11e9-8519-000d3ab1e588",
                    "name": null,
                    "ontologyproperty": "http://www.cidoc-crm.org/cidoc-crm/P1_is_identified_by",
                    "rangenode_id": "17891147-5ab5-11e9-aa2f-000d3ab1e588"
                },
                {
                    "description": null,
                    "domainnode_id": "17891140-5ab5-11e9-84ed-000d3ab1e588",
                    "edgeid": "17891160-5ab5-11e9-af13-000d3ab1e588",
                    "graph_id": "1789112e-5ab5-11e9-8519-000d3ab1e588",
                    "name": null,
                    "ontologyproperty": "http://www.cidoc-crm.org/cidoc-crm/P1_is_identified_by",
                    "rangenode_id": "17891148-5ab5-11e9-b825-000d3ab1e588"
                }
            ],
            "functions_x_graphs": [],
            "graphid": "1789112e-5ab5-11e9-8519-000d3ab1e588",
            "iconclass": "fa fa-plane",
            "is_editable": true,
            "isactive": true,
            "isresource": false,
            "jsonldcontext": null,
            "name": "Warden_Crash_Event",
            "nodegroups": [
                {
                    "cardinality": "1",
                    "legacygroupid": null,
                    "nodegroupid": "17891135-5ab5-11e9-921e-000d3ab1e588",
                    "parentnodegroup_id": "1789112f-5ab5-11e9-b464-000d3ab1e588"
                },
                {
                    "cardinality": "1",
                    "legacygroupid": null,
                    "nodegroupid": "17891132-5ab5-11e9-9168-000d3ab1e588",
                    "parentnodegroup_id": "1789112f-5ab5-11e9-b464-000d3ab1e588"
                },
                {
                    "cardinality": "1",
                    "legacygroupid": null,
                    "nodegroupid": "1789112f-5ab5-11e9-b464-000d3ab1e588",
                    "parentnodegroup_id": null
                }
            ],
            "nodes": [
                {
                    "config": null,
                    "datatype": "semantic",
                    "description": "",
                    "exportable": false,
                    "fieldname": "",
                    "graph_id": "1789112e-5ab5-11e9-8519-000d3ab1e588",
                    "is_collector": true,
                    "isrequired": false,
                    "issearchable": true,
                    "istopnode": true,
                    "name": "Warden_Crash_Event",
                    "nodegroup_id": "1789112f-5ab5-11e9-b464-000d3ab1e588",
                    "nodeid": "1789112f-5ab5-11e9-b464-000d3ab1e588",
                    "ontologyclass": "http://www.cidoc-crm.org/cidoc-crm/E81_Transformation",
                    "parentproperty": "",
                    "sortorder": 0
                },
                {
                    "config": {
                        "fillColor": "rgba(233,112,111,0.8)"
                    },
                    "datatype": "semantic",
                    "description": "",
                    "exportable": false,
                    "fieldname": "",
                    "graph_id": "1789112e-5ab5-11e9-8519-000d3ab1e588",
                    "is_collector": true,
                    "isrequired": false,
                    "issearchable": true,
                    "istopnode": false,
                    "name": "Crash_Descriptions",
                    "nodegroup_id": "17891132-5ab5-11e9-9168-000d3ab1e588",
                    "nodeid": "17891132-5ab5-11e9-9168-000d3ab1e588",
                    "ontologyclass": "http://www.cidoc-crm.org/cidoc-crm/E13_Attribute_Assignment",
                    "parentproperty": "http://www.cidoc-crm.org/cidoc-crm/P141i_was_assigned_by",
                    "sortorder": 0
                },
                {
                    "config": null,
                    "datatype": "semantic",
                    "description": "Represents a single node in a graph",
                    "exportable": false,
                    "fieldname": "",
                    "graph_id": "1789112e-5ab5-11e9-8519-000d3ab1e588",
                    "is_collector": true,
                    "isrequired": false,
                    "issearchable": true,
                    "istopnode": false,
                    "name": "Warden_Cargo",
                    "nodegroup_id": "17891135-5ab5-11e9-921e-000d3ab1e588",
                    "nodeid": "17891135-5ab5-11e9-921e-000d3ab1e588",
                    "ontologyclass": "http://www.cidoc-crm.org/cidoc-crm/E19_Physical_Object",
                    "parentproperty": "http://www.cidoc-crm.org/cidoc-crm/P12_occurred_in_the_presence_of",
                    "sortorder": 0
                },
                {
                    "config": null,
                    "datatype": "string",
                    "description": "Represents a single node in a graph",
                    "exportable": false,
                    "fieldname": "",
                    "graph_id": "1789112e-5ab5-11e9-8519-000d3ab1e588",
                    "is_collector": false,
                    "isrequired": false,
                    "issearchable": true,
                    "istopnode": false,
                    "name": "Last Flight Description",
                    "nodegroup_id": "17891132-5ab5-11e9-9168-000d3ab1e588",
                    "nodeid": "17891138-5ab5-11e9-a583-000d3ab1e588",
                    "ontologyclass": "http://www.cidoc-crm.org/cidoc-crm/E62_String",
                    "parentproperty": "http://www.cidoc-crm.org/cidoc-crm/P3_has_note",
                    "sortorder": 0
                },
                {
                    "config": {
                        "rdmCollection": "2c2b1956-6915-4709-971d-ca6d8d2d2a5d"
                    },
                    "datatype": "concept",
                    "description": "Represents a single node in a graph",
                    "exportable": false,
                    "fieldname": "",
                    "graph_id": "1789112e-5ab5-11e9-8519-000d3ab1e588",
                    "is_collector": false,
                    "isrequired": false,
                    "issearchable": true,
                    "istopnode": false,
                    "name": "Last Flight Description Type",
                    "nodegroup_id": "17891132-5ab5-11e9-9168-000d3ab1e588",
                    "nodeid": "17891139-5ab5-11e9-9b34-000d3ab1e588",
                    "ontologyclass": "http://www.cidoc-crm.org/cidoc-crm/E55_Type",
                    "parentproperty": "http://www.cidoc-crm.org/cidoc-crm/P2_has_type",
                    "sortorder": 0
                },
                {
                    "config": null,
                    "datatype": "semantic",
                    "description": "Represents a single node in a graph",
                    "exportable": false,
                    "fieldname": "",
                    "graph_id": "1789112e-5ab5-11e9-8519-000d3ab1e588",
                    "is_collector": false,
                    "isrequired": false,
                    "issearchable": true,
                    "istopnode": false,
                    "name": "Warden_Crew",
                    "nodegroup_id": "1789112f-5ab5-11e9-b464-000d3ab1e588",
                    "nodeid": "1789113a-5ab5-11e9-a3b4-000d3ab1e588",
                    "ontologyclass": "http://www.cidoc-crm.org/cidoc-crm/E74_Group",
                    "parentproperty": "http://www.cidoc-crm.org/cidoc-crm/P11_had_participant",
                    "sortorder": 0
                },
                {
                    "config": null,
                    "datatype": "semantic",
                    "description": "Represents a single node in a graph",
                    "exportable": false,
                    "fieldname": "",
                    "graph_id": "1789112e-5ab5-11e9-8519-000d3ab1e588",
                    "is_collector": false,
                    "isrequired": false,
                    "issearchable": true,
                    "istopnode": false,
                    "name": "Crew member",
                    "nodegroup_id": "1789112f-5ab5-11e9-b464-000d3ab1e588",
                    "nodeid": "1789113b-5ab5-11e9-ac12-000d3ab1e588",
                    "ontologyclass": "http://www.cidoc-crm.org/cidoc-crm/E21_Person",
                    "parentproperty": "http://www.cidoc-crm.org/cidoc-crm/P107_has_current_or_former_member",
                    "sortorder": 0
                },
                {
                    "config": {
                        "rdmCollection": "1d705d4c-88ec-4394-bb9a-ce30ec7fbdec"
                    },
                    "datatype": "concept-list",
                    "description": "Represents a single node in a graph",
                    "exportable": false,
                    "fieldname": "",
                    "graph_id": "1789112e-5ab5-11e9-8519-000d3ab1e588",
                    "is_collector": false,
                    "isrequired": false,
                    "issearchable": true,
                    "istopnode": false,
                    "name": "Crew Role",
                    "nodegroup_id": "1789112f-5ab5-11e9-b464-000d3ab1e588",
                    "nodeid": "1789113c-5ab5-11e9-b9c3-000d3ab1e588",
                    "ontologyclass": "http://www.cidoc-crm.org/cidoc-crm/E55_Type",
                    "parentproperty": "http://www.cidoc-crm.org/cidoc-crm/P2_has_type",
                    "sortorder": 0
                },
                {
                    "config": null,
                    "datatype": "string",
                    "description": "Represents a single node in a graph",
                    "exportable": false,
                    "fieldname": "",
                    "graph_id": "1789112e-5ab5-11e9-8519-000d3ab1e588",
                    "is_collector": false,
                    "isrequired": false,
                    "issearchable": true,
                    "istopnode": false,
                    "name": "Crew Member Name",
                    "nodegroup_id": "1789112f-5ab5-11e9-b464-000d3ab1e588",
                    "nodeid": "1789113d-5ab5-11e9-8c49-000d3ab1e588",
                    "ontologyclass": "http://www.cidoc-crm.org/cidoc-crm/E41_Appellation",
                    "parentproperty": "http://www.cidoc-crm.org/cidoc-crm/P1_is_identified_by",
                    "sortorder": 0
                },
                {
                    "config": {
                        "rdmCollection": "d2b35bce-b10a-4935-b50b-64d7eb433503"
                    },
                    "datatype": "concept-list",
                    "description": "Represents a single node in a graph",
                    "exportable": false,
                    "fieldname": "",
                    "graph_id": "1789112e-5ab5-11e9-8519-000d3ab1e588",
                    "is_collector": false,
                    "isrequired": false,
                    "issearchable": true,
                    "istopnode": false,
                    "name": "Cargo Type",
                    "nodegroup_id": "17891135-5ab5-11e9-921e-000d3ab1e588",
                    "nodeid": "1789113e-5ab5-11e9-a068-000d3ab1e588",
                    "ontologyclass": "http://www.cidoc-crm.org/cidoc-crm/E55_Type",
                    "parentproperty": "http://www.cidoc-crm.org/cidoc-crm/P2_has_type",
                    "sortorder": 0
                },
                {
                    "config": null,
                    "datatype": "date",
                    "description": null,
                    "exportable": false,
                    "fieldname": "",
                    "graph_id": "1789112e-5ab5-11e9-8519-000d3ab1e588",
                    "is_collector": false,
                    "isrequired": false,
                    "issearchable": true,
                    "istopnode": false,
                    "name": "Date of Loss",
                    "nodegroup_id": "1789112f-5ab5-11e9-b464-000d3ab1e588",
                    "nodeid": "1789113f-5ab5-11e9-9c10-000d3ab1e588",
                    "ontologyclass": "http://www.cidoc-crm.org/cidoc-crm/E50_Date",
                    "parentproperty": "http://www.cidoc-crm.org/cidoc-crm/P1_is_identified_by",
                    "sortorder": 0
                },
                {
                    "config": null,
                    "datatype": "semantic",
                    "description": null,
                    "exportable": false,
                    "fieldname": "",
                    "graph_id": "1789112e-5ab5-11e9-8519-000d3ab1e588",
                    "is_collector": false,
                    "isrequired": false,
                    "issearchable": true,
                    "istopnode": false,
                    "name": "Place of Departure",
                    "nodegroup_id": "1789112f-5ab5-11e9-b464-000d3ab1e588",
                    "nodeid": "17891140-5ab5-11e9-84ed-000d3ab1e588",
                    "ontologyclass": "http://www.cidoc-crm.org/cidoc-crm/E53_Place",
                    "parentproperty": "http://www.cidoc-crm.org/cidoc-crm/P161_has_spatial_projection",
                    "sortorder": 0
                },
                {
                    "config": null,
                    "datatype": "date",
                    "description": null,
                    "exportable": false,
                    "fieldname": "",
                    "graph_id": "1789112e-5ab5-11e9-8519-000d3ab1e588",
                    "is_collector": false,
                    "isrequired": false,
                    "issearchable": true,
                    "istopnode": false,
                    "name": "Expected Date of Arrival",
                    "nodegroup_id": "1789112f-5ab5-11e9-b464-000d3ab1e588",
                    "nodeid": "17891141-5ab5-11e9-a4a7-000d3ab1e588",
                    "ontologyclass": "http://www.cidoc-crm.org/cidoc-crm/E50_Date",
                    "parentproperty": "http://www.cidoc-crm.org/cidoc-crm/P1_is_identified_by",
                    "sortorder": 0
                },
                {
                    "config": null,
                    "datatype": "semantic",
                    "description": null,
                    "exportable": false,
                    "fieldname": "",
                    "graph_id": "1789112e-5ab5-11e9-8519-000d3ab1e588",
                    "is_collector": false,
                    "isrequired": false,
                    "issearchable": true,
                    "istopnode": false,
                    "name": "Voyage Time Span",
                    "nodegroup_id": "1789112f-5ab5-11e9-b464-000d3ab1e588",
                    "nodeid": "17891142-5ab5-11e9-a89e-000d3ab1e588",
                    "ontologyclass": "http://www.cidoc-crm.org/cidoc-crm/E52_Time-Span",
                    "parentproperty": "http://www.cidoc-crm.org/cidoc-crm/P4_has_time-span",
                    "sortorder": 0
                },
                {
                    "config": {
                        "rdmCollection": "a0e81fa0-9a3a-42d5-978f-31c9dad13aa7"
                    },
                    "datatype": "concept",
                    "description": null,
                    "exportable": false,
                    "fieldname": "",
                    "graph_id": "1789112e-5ab5-11e9-8519-000d3ab1e588",
                    "is_collector": false,
                    "isrequired": false,
                    "issearchable": true,
                    "istopnode": false,
                    "name": "Site Type",
                    "nodegroup_id": "1789112f-5ab5-11e9-b464-000d3ab1e588",
                    "nodeid": "17891143-5ab5-11e9-9139-000d3ab1e588",
                    "ontologyclass": "http://www.cidoc-crm.org/cidoc-crm/E55_Type",
                    "parentproperty": "http://www.cidoc-crm.org/cidoc-crm/P2_has_type",
                    "sortorder": 0
                },
                {
                    "config": null,
                    "datatype": "semantic",
                    "description": null,
                    "exportable": false,
                    "fieldname": "",
                    "graph_id": "1789112e-5ab5-11e9-8519-000d3ab1e588",
                    "is_collector": false,
                    "isrequired": false,
                    "issearchable": true,
                    "istopnode": false,
                    "name": "Crash Site",
                    "nodegroup_id": "1789112f-5ab5-11e9-b464-000d3ab1e588",
                    "nodeid": "17891144-5ab5-11e9-92e9-000d3ab1e588",
                    "ontologyclass": "http://www.cidoc-crm.org/cidoc-crm/E18_Physical_Thing",
                    "parentproperty": "http://www.cidoc-crm.org/cidoc-crm/P92_brought_into_existence",
                    "sortorder": 0
                },
                {
                    "config": null,
                    "datatype": "date",
                    "description": null,
                    "exportable": false,
                    "fieldname": "",
                    "graph_id": "1789112e-5ab5-11e9-8519-000d3ab1e588",
                    "is_collector": false,
                    "isrequired": false,
                    "issearchable": true,
                    "istopnode": false,
                    "name": "Date of Departure",
                    "nodegroup_id": "1789112f-5ab5-11e9-b464-000d3ab1e588",
                    "nodeid": "17891145-5ab5-11e9-8d94-000d3ab1e588",
                    "ontologyclass": "http://www.cidoc-crm.org/cidoc-crm/E50_Date",
                    "parentproperty": "http://www.cidoc-crm.org/cidoc-crm/P1_is_identified_by",
                    "sortorder": 0
                },
                {
                    "config": null,
                    "datatype": "semantic",
                    "description": null,
                    "exportable": false,
                    "fieldname": "",
                    "graph_id": "1789112e-5ab5-11e9-8519-000d3ab1e588",
                    "is_collector": false,
                    "isrequired": false,
                    "issearchable": true,
                    "istopnode": false,
                    "name": "Place of Destination",
                    "nodegroup_id": "1789112f-5ab5-11e9-b464-000d3ab1e588",
                    "nodeid": "17891146-5ab5-11e9-a3a2-000d3ab1e588",
                    "ontologyclass": "http://www.cidoc-crm.org/cidoc-crm/E53_Place",
                    "parentproperty": "http://www.cidoc-crm.org/cidoc-crm/P161_has_spatial_projection",
                    "sortorder": 0
                },
                {
                    "config": {
                        "rdmCollection": "e9adad02-1ed9-4370-b9e5-9547413bc77c"
                    },
                    "datatype": "concept",
                    "description": null,
                    "exportable": false,
                    "fieldname": "",
                    "graph_id": "1789112e-5ab5-11e9-8519-000d3ab1e588",
                    "is_collector": false,
                    "isrequired": false,
                    "issearchable": true,
                    "istopnode": false,
                    "name": "Place of Destination Name",
                    "nodegroup_id": "1789112f-5ab5-11e9-b464-000d3ab1e588",
                    "nodeid": "17891147-5ab5-11e9-aa2f-000d3ab1e588",
                    "ontologyclass": "http://www.cidoc-crm.org/cidoc-crm/E41_Appellation",
                    "parentproperty": "http://www.cidoc-crm.org/cidoc-crm/P1_is_identified_by",
                    "sortorder": 0
                },
                {
                    "config": {
                        "rdmCollection": "e9adad02-1ed9-4370-b9e5-9547413bc77c"
                    },
                    "datatype": "concept",
                    "description": null,
                    "exportable": false,
                    "fieldname": "",
                    "graph_id": "1789112e-5ab5-11e9-8519-000d3ab1e588",
                    "is_collector": false,
                    "isrequired": false,
                    "issearchable": true,
                    "istopnode": false,
                    "name": "Place of Departure Name",
                    "nodegroup_id": "1789112f-5ab5-11e9-b464-000d3ab1e588",
                    "nodeid": "17891148-5ab5-11e9-b825-000d3ab1e588",
                    "ontologyclass": "http://www.cidoc-crm.org/cidoc-crm/E41_Appellation",
                    "parentproperty": "http://www.cidoc-crm.org/cidoc-crm/P1_is_identified_by",
                    "sortorder": 0
                },
                {
                    "config": {
                        "rdmCollection": "5a3fe6a9-cdab-4420-8fa7-1cbc4b7e6cbe"
                    },
                    "datatype": "concept",
                    "description": null,
                    "exportable": false,
                    "fieldname": "",
                    "graph_id": "1789112e-5ab5-11e9-8519-000d3ab1e588",
                    "is_collector": false,
                    "isrequired": false,
                    "issearchable": true,
                    "istopnode": false,
                    "name": "Manner of Loss",
                    "nodegroup_id": "1789112f-5ab5-11e9-b464-000d3ab1e588",
                    "nodeid": "17891149-5ab5-11e9-b0c3-000d3ab1e588",
                    "ontologyclass": "http://www.cidoc-crm.org/cidoc-crm/E55_Type",
                    "parentproperty": "http://www.cidoc-crm.org/cidoc-crm/P2_has_type",
                    "sortorder": 0
                },
                {
                    "config": {
                        "rdmCollection": "e1451a0b-4f3b-41f8-aa83-44ab9c6235b1"
                    },
                    "datatype": "concept",
                    "description": null,
                    "exportable": false,
                    "fieldname": "",
                    "graph_id": "1789112e-5ab5-11e9-8519-000d3ab1e588",
                    "is_collector": false,
                    "isrequired": false,
                    "issearchable": true,
                    "istopnode": false,
                    "name": "Flight Type",
                    "nodegroup_id": "1789112f-5ab5-11e9-b464-000d3ab1e588",
                    "nodeid": "1789114a-5ab5-11e9-8b04-000d3ab1e588",
                    "ontologyclass": "http://www.cidoc-crm.org/cidoc-crm/E55_Type",
                    "parentproperty": "http://www.cidoc-crm.org/cidoc-crm/P2_has_type",
                    "sortorder": 0
                }
            ],
            "ontology_id": "e6e8db47-2ccf-11e6-927e-b8f6b115d7dd",
            "relatable_resource_model_ids": [],
            "resource_2_resource_constraints": [],
            "root": {
                "config": null,
                "datatype": "semantic",
                "description": "",
                "exportable": false,
                "fieldname": "",
                "graph_id": "1789112e-5ab5-11e9-8519-000d3ab1e588",
                "is_collector": true,
                "isrequired": false,
                "issearchable": true,
                "istopnode": true,
                "name": "Warden_Crash_Event",
                "nodegroup_id": "1789112f-5ab5-11e9-b464-000d3ab1e588",
                "nodeid": "1789112f-5ab5-11e9-b464-000d3ab1e588",
                "ontologyclass": "http://www.cidoc-crm.org/cidoc-crm/E81_Transformation",
                "sortorder": 0
            },
            "slug": null,
            "subtitle": "Used to record the event in which an aircraft was lost.",
            "template_id": "50000000-0000-0000-0000-000000000001",
            "version": ""
        }
    ]
}